bologna/__init__.py
bologna/di.py
bologna-0.2.3.dist-info/WHEEL
bologna-0.2.3.dist-info/METADATA
bologna-0.2.3.dist-info/RECORD
