Metadata-Version: 2.1
Name: bologna
Version: 0.2.3
Summary: A tiny no-faff dependency injection module for python.
Home-page: https://github.com/aap007freak/tinydi
License: MIT
Author: Anton Leagre
Requires-Python: >=3.9,<4.0
Classifier: License :: OSI Approved :: MIT License
Classifier: Programming Language :: Python :: 3
Project-URL: Repository, https://github.com/aap007freak/tinydi
